[{"__type__":"cc.SpriteFrame","content":{"name":"role_cannon08_body01","texture":"aemejFqxpO5I3seuP69wPV","rect":[2,547,86,163],"offset":[0,0],"originalSize":[86,163],"capInsets":[0,0,0,0]}},{"__type__":"cc.SpriteFrame","content":{"name":"role_cannon08_body03","texture":"aemejFqxpO5I3seuP69wPV","rect":[295,444,86,163],"offset":[0,0],"originalSize":[86,163],"capInsets":[0,0,0,0]}},{"__type__":"cc.SpriteFrame","content":{"name":"role_cannon08_body02","texture":"aemejFqxpO5I3seuP69wPV","rect":[200,539,86,163],"offset":[0,0],"originalSize":[86,163],"capInsets":[0,0,0,0]}},[{"__type__":"cc.Prefab","_name":"cannon8","data":{"__id__":1}},{"__type__":"cc.Node","_name":"cannon8","_children":[{"__id__":2},{"__id__":3}],"_components":[{"__type__":"66b4exMdbtFPLDXbh6GmOUL","node":{"__id__":1},"node_body":{"__id__":3},"node_wheels":{"__id__":2}}],"_prefab":{"__type__":"cc.PrefabInfo","root":{"__id__":1},"asset":{"__uuid__":"75oXCOcvNG+LbLvRszodD8"},"fileId":"16QknsB79F8qhMFRRt4ULO"},"_contentSize":{"__type__":"cc.Size","width":35,"height":80},"_trs":{"__type__":"TypedArray","ctor":"Float64Array","array":[-1859,100,0,0,0,0,1,1,1,1]},"_zIndex":0,"_groupIndex":5,"groupIndex":5},{"__type__":"cc.Node","_name":"wheels","_parent":{"__id__":1},"_active":false,"_prefab":{"__type__":"cc.PrefabInfo","root":{"__id__":1},"asset":{"__uuid__":"75oXCOcvNG+LbLvRszodD8"},"fileId":"55zEwB9DdKwI2S/XrsXTLp"},"_trs":{"__type__":"TypedArray","ctor":"Float64Array","array":[0,0,0,0,0,0,1,1,1,1]},"_zIndex":0},{"__type__":"cc.Node","_name":"anima","_parent":{"__id__":1},"_children":[{"__id__":4},{"__id__":6}],"_components":[{"__type__":"cd960M+oPlOA46IO//KtmHM","node":{"__id__":3}}],"_prefab":{"__type__":"cc.PrefabInfo","root":{"__id__":1},"asset":{"__uuid__":"75oXCOcvNG+LbLvRszodD8"},"fileId":"95x4y9lt9OtLVVssB69sxK"},"_trs":{"__type__":"TypedArray","ctor":"Float64Array","array":[0,0,0,0,0,0,1,1,1,1]},"_zIndex":0},{"__type__":"cc.Node","_name":"normal","_parent":{"__id__":3},"_children":[{"__id__":5}],"_components":[{"__type__":"a1afbrq6LlK/4xrv5Pf7p6Z","node":{"__id__":4}}],"_prefab":{"__type__":"cc.PrefabInfo","root":{"__id__":1},"asset":{"__uuid__":"75oXCOcvNG+LbLvRszodD8"},"fileId":"d1TdNRMYNItb7J//RTwRuX"},"_trs":{"__type__":"TypedArray","ctor":"Float64Array","array":[0,0,0,0,0,0,1,1,1,1]},"_zIndex":0},{"__type__":"cc.Node","_name":"role_cannon08_body01","_parent":{"__id__":4},"_components":[{"__type__":"cc.Sprite","node":{"__id__":5},"_spriteFrame":{"__uuid__":"22v0PszlNDqp5ddf2ib+I+"}}],"_prefab":{"__type__":"cc.PrefabInfo","root":{"__id__":1},"asset":{"__uuid__":"75oXCOcvNG+LbLvRszodD8"},"fileId":"08prEQflFOMbXCrZsL4+mJ"},"_contentSize":{"__type__":"cc.Size","width":86,"height":163},"_trs":{"__type__":"TypedArray","ctor":"Float64Array","array":[0,0,0,0,0,0,1,1,1,1]},"_zIndex":0},{"__type__":"cc.Node","_name":"attack","_parent":{"__id__":3},"_children":[{"__id__":7},{"__id__":8}],"_active":false,"_components":[{"__type__":"a1afbrq6LlK/4xrv5Pf7p6Z","node":{"__id__":6}}],"_prefab":{"__type__":"cc.PrefabInfo","root":{"__id__":1},"asset":{"__uuid__":"75oXCOcvNG+LbLvRszodD8"},"fileId":"2b/7Bbdg9MqZWo6Kw+N6+G"},"_trs":{"__type__":"TypedArray","ctor":"Float64Array","array":[0,0,0,0,0,0,1,1,1,1]},"_zIndex":0},{"__type__":"cc.Node","_name":"role_cannon08_body02","_parent":{"__id__":6},"_components":[{"__type__":"cc.Sprite","node":{"__id__":7},"_spriteFrame":{"__uuid__":"70indqQpBEEoQaLPqZk2Ji"}}],"_prefab":{"__type__":"cc.PrefabInfo","root":{"__id__":1},"asset":{"__uuid__":"75oXCOcvNG+LbLvRszodD8"},"fileId":"f5u2HbIQpCbZ7P2I2uOLbT"},"_contentSize":{"__type__":"cc.Size","width":86,"height":163},"_trs":{"__type__":"TypedArray","ctor":"Float64Array","array":[0,0,0,0,0,0,1,1,1,1]},"_zIndex":0},{"__type__":"cc.Node","_name":"role_cannon08_body03","_parent":{"__id__":6},"_components":[{"__type__":"cc.Sprite","node":{"__id__":8},"_spriteFrame":{"__uuid__":"5093HsOwVC4aXv2Si4bejs"}}],"_prefab":{"__type__":"cc.PrefabInfo","root":{"__id__":1},"asset":{"__uuid__":"75oXCOcvNG+LbLvRszodD8"},"fileId":"1f2g8PZ3lMm6KE+R0IisL8"},"_contentSize":{"__type__":"cc.Size","width":86,"height":163},"_trs":{"__type__":"TypedArray","ctor":"Float64Array","array":[0,0,0,0,0,0,1,1,1,1]},"_zIndex":0}]]